opensr_usecases/__init__.py
opensr_usecases/validator.py
opensr_usecases/data/__init__.py
opensr_usecases/data/placeholder_dataset.py
opensr_usecases/models/__init__.py
opensr_usecases/models/placeholder_model.py
opensr_usecases/object_detection/__init__.py
opensr_usecases/object_detection/object_detection_utils.py
opensr_usecases/segmentation/__init__.py
opensr_usecases/segmentation/segmentation_utils.py
opensr_usecases/utils/__init__.py
opensr_usecases/utils/dict_average.py
opensr_usecases/utils/other_utils.py
opensr_usecases/utils/pretty_print_df.py
opensr_usecases/utils/pretty_print_metrics.py
opensr_usecases-0.2.8.dist-info/METADATA
opensr_usecases-0.2.8.dist-info/WHEEL
opensr_usecases-0.2.8.dist-info/top_level.txt
opensr_usecases-0.2.8.dist-info/RECORD
