Metadata-Version: 2.4
Name: opensr-usecases
Version: 0.2.8
Summary: Use-case-based validation for SR products.
Home-page: https://github.com/ESAOpenSR/opensr-usecases
Author: Simon Donike
Author-email: simon@donike.net
Classifier: Programming Language :: Python :: 3
Classifier: License :: OSI Approved :: MIT License
Classifier: Operating System :: OS Independent
Requires-Dist: numpy
Requires-Dist: torch
Requires-Dist: tqdm
Requires-Dist: prettytable
Requires-Dist: Pillow
Dynamic: author
Dynamic: author-email
Dynamic: classifier
Dynamic: description
Dynamic: description-content-type
Dynamic: home-page
Dynamic: requires-dist
Dynamic: summary
